libmft/__init__.py
libmft/api.py
libmft/attribute.py
libmft/exceptions.py
libmft/flagsandtypes.py
libmft/util/__init__.py
libmft/util/functions.py
libmft-0.8.dist-info/LICENSE
libmft-0.8.dist-info/METADATA
libmft-0.8.dist-info/WHEEL
libmft-0.8.dist-info/top_level.txt
libmft-0.8.dist-info/RECORD
