Metadata-Version: 2.1
Name: libmft
Version: 0.8
Summary: A pure python library to parse MFT entries
Home-page: https://github.com/jldantas/libmft
Author: Julio Dantas
License: BSD 3-Clause
Keywords: mft parser library python
Platform: UNKNOWN
Classifier: Development Status :: 5 - Production/Stable
Classifier: Intended Audience :: Developers
Classifier: Intended Audience :: Information Technology
Classifier: License :: OSI Approved :: BSD License
Classifier: Operating System :: OS Independent
Classifier: Programming Language :: Python :: 3.6
Classifier: Topic :: Security
Classifier: Topic :: Software Development :: Libraries :: Python Modules
Requires-Python: >=3.6
